src/async_fifo.v
module async_fifo #(
    parameter DATA_WIDTH = 8,
    parameter ADDR_WIDTH = 4
)(
    input  wire                     wr_clk,
    input  wire                     wr_rst,
    input  wire                     wr_en,
    input  wire [DATA_WIDTH-1:0]    wr_data,
    output wire                     wr_full,

    input  wire                     rd_clk,
    input  wire                     rd_rst,
    input  wire                     rd_en,
    output reg  [DATA_WIDTH-1:0]    rd_data,   // <-- now registered
    output wire                     rd_empty
);
    localparam DEPTH = 1 << ADDR_WIDTH;

    // ---------------------------------------------------------
    // Storage
    // ---------------------------------------------------------
    reg [DATA_WIDTH-1:0] mem [0:DEPTH-1];

    // ---------------------------------------------------------
    // Binary & Gray pointers (ADDR_WIDTH+1 to detect wrap)
    // ---------------------------------------------------------
    reg  [ADDR_WIDTH:0] wr_ptr, rd_ptr;
    reg  [ADDR_WIDTH:0] wr_ptr_gray, rd_ptr_gray;

    // Next (incremented) binary/Gray pointers
    wire [ADDR_WIDTH:0] wr_ptr_bin_next = wr_ptr + 1'b1;
    wire [ADDR_WIDTH:0] rd_ptr_bin_next = rd_ptr + 1'b1;

    // Binary to Gray
    function [ADDR_WIDTH:0] bin2gray;
        input [ADDR_WIDTH:0] bin;
        begin
            bin2gray = bin ^ (bin >> 1);
        end
    endfunction

    wire [ADDR_WIDTH:0] wr_ptr_gray_next = bin2gray(wr_ptr_bin_next);
    wire [ADDR_WIDTH:0] rd_ptr_gray_next = bin2gray(rd_ptr_bin_next);

    // ---------------------------------------------------------
    // 2-flop synchronizers for CDC
    // ---------------------------------------------------------
    reg [ADDR_WIDTH:0] rd_ptr_gray_sync1, rd_ptr_gray_sync2;
    reg [ADDR_WIDTH:0] wr_ptr_gray_sync1, wr_ptr_gray_sync2;

    // ---------------------------------------------------------
    // Status flags
    // ---------------------------------------------------------
    assign wr_full =
        (wr_ptr_gray_next == {~rd_ptr_gray_sync2[ADDR_WIDTH:ADDR_WIDTH-1],
                               rd_ptr_gray_sync2[ADDR_WIDTH-2:0]});

    assign rd_empty = (rd_ptr_gray == wr_ptr_gray_sync2);

    // ---------------------------------------------------------
    // WRITE DOMAIN
    // ---------------------------------------------------------
    always @(posedge wr_clk or posedge wr_rst) begin
        if (wr_rst) begin
            wr_ptr      <= { (ADDR_WIDTH+1){1'b0} };
            wr_ptr_gray <= { (ADDR_WIDTH+1){1'b0} };
        end else begin
            if (wr_en && !wr_full) begin
                mem[wr_ptr[ADDR_WIDTH-1:0]] <= wr_data;
                wr_ptr      <= wr_ptr_bin_next;
                wr_ptr_gray <= wr_ptr_gray_next;
            end
        end
    end

    // Synchronize READ pointer into WRITE domain
    always @(posedge wr_clk or posedge wr_rst) begin
        if (wr_rst) begin
            rd_ptr_gray_sync1 <= { (ADDR_WIDTH+1){1'b0} };
            rd_ptr_gray_sync2 <= { (ADDR_WIDTH+1){1'b0} };
        end else begin
            rd_ptr_gray_sync1 <= rd_ptr_gray;
            rd_ptr_gray_sync2 <= rd_ptr_gray_sync1;
        end
    end

    // ---------------------------------------------------------
    // READ DOMAIN
    // ---------------------------------------------------------
    always @(posedge rd_clk or posedge rd_rst) begin
        if (rd_rst) begin
            rd_ptr      <= { (ADDR_WIDTH+1){1'b0} };
            rd_ptr_gray <= { (ADDR_WIDTH+1){1'b0} };
            rd_data     <= {DATA_WIDTH{1'b0}};   // reset data
        end else begin
            if (rd_en && !rd_empty) begin
                rd_data     <= mem[rd_ptr[ADDR_WIDTH-1:0]]; // <-- registered
                rd_ptr      <= rd_ptr_bin_next;
                rd_ptr_gray <= rd_ptr_gray_next;
            end
        end
    end

    // Synchronize WRITE pointer into READ domain
    always @(posedge rd_clk or posedge rd_rst) begin
        if (rd_rst) begin
            wr_ptr_gray_sync1 <= { (ADDR_WIDTH+1){1'b0} };
            wr_ptr_gray_sync2 <= { (ADDR_WIDTH+1){1'b0} };
        end else begin
            wr_ptr_gray_sync1 <= wr_ptr_gray;
            wr_ptr_gray_sync2 <= wr_ptr_gray_sync1;
        end
    end

endmodule

async_fifo_tb.v
`timescale 1ns/1ps

module async_fifo_tb;

  localparam DATA_WIDTH = 8;
  localparam ADDR_WIDTH = 4;
  localparam DEPTH      = 1 << ADDR_WIDTH;

  // DUT ports
  reg                   wr_clk, wr_rst, wr_en;
  reg  [DATA_WIDTH-1:0] wr_data;
  wire                  wr_full;

  reg                   rd_clk, rd_rst, rd_en;
  wire [DATA_WIDTH-1:0] rd_data;
  wire                  rd_empty;

  // Instantiate DUT
  async_fifo #(
    .DATA_WIDTH(DATA_WIDTH),
    .ADDR_WIDTH(ADDR_WIDTH)
  ) dut (
    .wr_clk   (wr_clk),
    .wr_rst   (wr_rst),
    .wr_en    (wr_en),
    .wr_data  (wr_data),
    .wr_full  (wr_full),

    .rd_clk   (rd_clk),
    .rd_rst   (rd_rst),
    .rd_en    (rd_en),
    .rd_data  (rd_data),
    .rd_empty (rd_empty)
  );

  // Clock generation
  initial wr_clk = 0;
  always  #5 wr_clk = ~wr_clk;   // 100 MHz

  initial rd_clk = 0;
  always  #7 rd_clk = ~rd_clk;   // ~71 MHz

  // Test procedure
  integer i;
  reg [DATA_WIDTH-1:0] expected;

  initial begin
    // VCD dump
    $dumpfile("async_fifo_tb.vcd");
    $dumpvars(0, async_fifo_tb);

    // Init
    wr_rst = 1;
    rd_rst = 1;
    wr_en  = 0;
    rd_en  = 0;
    wr_data = 0;

    // Release resets
    #20;
    wr_rst = 0;
    rd_rst = 0;

    // --------------------------------------------------------
    // WRITE PHASE
    // --------------------------------------------------------
    $display("[%0t] Starting writes...", $time);
    for (i = 0; i < 8; i = i+1) begin
      @(posedge wr_clk);
      if (!wr_full) begin
        wr_data = i;
        wr_en   = 1;
        $display("[%0t] WRITE %0d", $time, wr_data);
      end
    end
    @(posedge wr_clk);
    wr_en = 0;

    // Small gap before reads
    #50;

    // --------------------------------------------------------
    // READ PHASE
    // --------------------------------------------------------
    $display("[%0t] Starting reads...", $time);
    for (i = 0; i < 8; i = i+1) begin
      expected = i;
      @(posedge rd_clk);
      if (!rd_empty) begin
        rd_en = 1;               // issue read
      end
      @(posedge rd_clk);          // wait one cycle for data
      rd_en = 0;
      if (rd_data !== expected)
        $display("[%0t] ERROR: Expected %0d, got %0d", $time, expected, rd_data);
      else
        $display("[%0t] OK: Read %0d", $time, rd_data);
    end

    // --------------------------------------------------------
    // FINISH
    // --------------------------------------------------------
    #100;
    $display("[%0t] TESTBENCH FINISHED", $time);
    $finish;
  end

endmodule

async_fifo_tb.vcd
$date
	Fri Aug 29 07:21:41 2025
$end
$version
	Icarus Verilog
$end
$timescale
	1ps
$end
$scope module async_fifo_tb $end
$var wire 1 ! wr_full $end
$var wire 1 " rd_empty $end
$var wire 8 # rd_data [7:0] $end
$var parameter 32 $ ADDR_WIDTH $end
$var parameter 32 % DATA_WIDTH $end
$var parameter 36 & DEPTH $end
$var reg 8 ' expected [7:0] $end
$var reg 1 ( rd_clk $end
$var reg 1 ) rd_en $end
$var reg 1 * rd_rst $end
$var reg 1 + wr_clk $end
$var reg 8 , wr_data [7:0] $end
$var reg 1 - wr_en $end
$var reg 1 . wr_rst $end
$var integer 32 / i [31:0] $end
$scope module dut $end
$var wire 1 ( rd_clk $end
$var wire 1 ) rd_en $end
$var wire 1 * rd_rst $end
$var wire 1 + wr_clk $end
$var wire 8 0 wr_data [7:0] $end
$var wire 1 - wr_en $end
$var wire 1 . wr_rst $end
$var wire 5 1 wr_ptr_gray_next [4:0] $end
$var wire 5 2 wr_ptr_bin_next [4:0] $end
$var wire 1 ! wr_full $end
$var wire 5 3 rd_ptr_gray_next [4:0] $end
$var wire 5 4 rd_ptr_bin_next [4:0] $end
$var wire 1 " rd_empty $end
$var parameter 32 5 ADDR_WIDTH $end
$var parameter 32 6 DATA_WIDTH $end
$var parameter 36 7 DEPTH $end
$var reg 8 8 rd_data [7:0] $end
$var reg 5 9 rd_ptr [4:0] $end
$var reg 5 : rd_ptr_gray [4:0] $end
$var reg 5 ; rd_ptr_gray_sync1 [4:0] $end
$var reg 5 < rd_ptr_gray_sync2 [4:0] $end
$var reg 5 = wr_ptr [4:0] $end
$var reg 5 > wr_ptr_gray [4:0] $end
$var reg 5 ? wr_ptr_gray_sync1 [4:0] $end
$var reg 5 @ wr_ptr_gray_sync2 [4:0] $end
$scope function bin2gray $end
$var reg 5 A bin [4:0] $end
$upscope $end
$upscope $end
$upscope $end
$enddefinitions $end
$comment Show the parameter values. $end
$dumpall
b10000 7
b1000 6
b100 5
b10000 &
b1000 %
b100 $
$end
#0
$dumpvars
b1 A
b0 @
b0 ?
b0 >
b0 =
b0 <
b0 ;
b0 :
b0 9
b0 8
b1 4
b1 3
b1 2
b1 1
b0 0
bx /
1.
0-
b0 ,
0+
1*
0)
0(
bx '
b0 #
1"
0!
$end
#5000
1+
#7000
1(
#10000
0+
#14000
0(
#15000
1+
#20000
0+
b0 /
0*
0.
#21000
1(
#25000
b11 1
b10 A
b1 >
b10 2
b1 =
b1 /
1-
1+
#28000
0(
#30000
0+
#35000
b10 1
b11 A
b11 >
b11 2
b10 =
b1 ?
b10 /
b1 ,
b1 0
1+
1(
#40000
0+
#42000
0(
#45000
b110 1
b100 A
b10 >
b100 2
b11 =
b11 /
b10 ,
b10 0
1+
#49000
0"
b1 @
b10 ?
1(
#50000
0+
#55000
b111 1
b101 A
b110 >
b101 2
b100 =
b100 /
b11 ,
b11 0
1+
#56000
0(
#60000
0+
#63000
b10 @
b110 ?
1(
#65000
b101 1
b110 A
b111 >
b110 2
b101 =
b101 /
b100 ,
b100 0
1+
#70000
0+
0(
#75000
b100 1
b111 A
b101 >
b111 2
b110 =
b110 /
b101 ,
b101 0
1+
#77000
b110 @
b101 ?
1(
#80000
0+
#84000
0(
#85000
b1100 1
b1000 A
b100 >
b1000 2
b111 =
b111 /
b110 ,
b110 0
1+
#90000
0+
#91000
b101 @
b100 ?
1(
#95000
b1101 1
b1001 A
b1100 >
b1001 2
b1000 =
b1000 /
b111 ,
b111 0
1+
#98000
0(
#100000
0+
#105000
b100 @
b1100 ?
0-
1+
1(
#110000
0+
#112000
0(
#115000
1+
#119000
b1100 @
1(
#120000
0+
#125000
1+
#126000
0(
#130000
0+
#133000
1(
#135000
1+
#140000
0+
0(
#145000
1+
#147000
1(
#150000
0+
#154000
0(
#155000
1+
b0 '
b0 /
#160000
0+
#161000
b11 3
b10 A
b1 :
b10 4
b1 9
1)
1(
#165000
b1 ;
1+
#168000
0(
#170000
0+
#175000
b1 <
b1 '
b1 /
0)
1+
1(
#180000
0+
#182000
0(
#185000
1+
#189000
b10 3
b11 A
b11 :
b11 4
b10 9
b1 #
b1 8
1)
1(
#190000
0+
#195000
b11 ;
1+
#196000
0(
#200000
0+
#203000
b10 '
b10 /
0)
1(
#205000
b11 <
1+
#210000
0+
0(
#215000
1+
#217000
b110 3
b100 A
b10 :
b100 4
b11 9
b10 #
b10 8
1)
1(
#220000
0+
#224000
0(
#225000
b10 ;
1+
#230000
0+
#231000
b11 '
b11 /
0)
1(
#235000
b10 <
1+
#238000
0(
#240000
0+
#245000
b111 3
b101 A
b110 :
b101 4
b100 9
b11 #
b11 8
1)
1+
1(
#250000
0+
#252000
0(
#255000
b110 ;
1+
#259000
b100 '
b100 /
0)
1(
#260000
0+
#265000
b110 <
1+
#266000
0(
#270000
0+
#273000
b101 3
b110 A
b111 :
b110 4
b101 9
b100 #
b100 8
1)
1(
#275000
b111 ;
1+
#280000
0+
0(
#285000
b111 <
1+
#287000
b101 '
b101 /
0)
1(
#290000
0+
#294000
0(
#295000
1+
#300000
0+
#301000
b100 3
b111 A
b101 :
b111 4
b110 9
b101 #
b101 8
1)
1(
#305000
b101 ;
1+
#308000
0(
#310000
0+
#315000
b101 <
b110 '
b110 /
0)
1+
1(
#320000
0+
#322000
0(
#325000
1+
#329000
b1100 3
b1000 A
b100 :
b1000 4
b111 9
b110 #
b110 8
1)
1(
#330000
0+
#335000
b100 ;
1+
#336000
0(
#340000
0+
#343000
b111 '
b111 /
0)
1(
#345000
b100 <
1+
#350000
0+
0(
#355000
1+
#357000
b1101 3
b1001 A
1"
b1100 :
b1001 4
b1000 9
b111 #
b111 8
1)
1(
#360000
0+
#364000
0(
#365000
b1100 ;
1+
#370000
0+
#371000
b1000 /
0)
1(
#375000
b1100 <
1+
